harbinger/__init__.py
harbinger/__main__.py
harbinger/exceptions.py
harbinger/py.typed
harbinger/utils.py
harbinger/wrappers/flac.py
harbinger/wrappers/opusenc.py
harbinger-0.1.1.dist-info/METADATA
harbinger-0.1.1.dist-info/WHEEL
harbinger-0.1.1.dist-info/entry_points.txt
harbinger-0.1.1.dist-info/RECORD
